marc2aleph/__init__.py
marc2aleph/marc.py
marc2aleph-0.0.2.dist-info/LICENSE
marc2aleph-0.0.2.dist-info/METADATA
marc2aleph-0.0.2.dist-info/WHEEL
marc2aleph-0.0.2.dist-info/top_level.txt
marc2aleph-0.0.2.dist-info/RECORD
