Metadata-Version: 2.1
Name: marc2aleph
Version: 0.0.2
Summary: Conversion from MARC(2709) to Aleph sequential and vice-versa
Home-page: https://github.com/turricula/marc2aleph
Author: zhv
License: UNKNOWN
Platform: UNKNOWN
Classifier: Development Status :: 3 - Alpha
Classifier: Intended Audience :: Developers
Classifier: Programming Language :: Python :: 3
Classifier: License :: OSI Approved :: GNU General Public License v3 (GPLv3)
Classifier: Operating System :: OS Independent
Requires-Python: >=3.6
